<sect2>
<title>Introduction à control-center</title>

<screen>Site de téléchargement (HTTP):       <ulink url="&control-center-download-http;"/>
Site de téléchargement (FTP):        <ulink url="&control-center-download-ftp;"/>
Version utilisée:                   &control-center-version;
Taille du package:                   &control-center-size;
Estimation de l'espace disque requis:  &control-center-buildsize;</screen>

<para>Le package control-center contient les gestionnaires de paramétrages
GNOME.</para>

<screen>control-center dépends de
<xref linkend="gnome-desktop"/> et <xref linkend="metacity"/></screen>

</sect2>
