<sect2>
<title>Introduction à gail</title>

<screen>Site de téléchargement (HTTP):  <ulink url="&gail-download-http;"/>
Site de téléchargement (FTP):           <ulink url="&gail-download-ftp;"/>
Version utilisée:                       &gail-version;
Taille du package:                      &gail-size;
Estimation de l'espace disque requis:   &gail-buildsize;
Estimation du temps de construction:    &gail-time;</screen>

<para>Le package gail contient les bibliothèques d'implémentation de
l'accessibilité Gnome (Gnome Accessibility Implementation Libraries).</para>

<screen>gail dépend de
<xref linkend="GTK2"/> et <xref linkend="libgnomecanvas"/>
gail utilisera:
<xref linkend="gtk-doc"/> et <xref linkend="sgml-dtd-3"/></screen>

</sect2>
