<sect2><title>Contenu de Kernel-&kernel-contversion;</title><sect3><title>Support Files</title><para>Le noyau linux et les entêtes du noyau linux</para></sect3><sect3><title>Descriptions</title><sect4><title>noyau linux</title><para>Le noyau de Linux est au coeur de chaque système Linux. C'est luiqui fait tourner Linux. Quand vous allumez votre ordinateur et démarrezun système Linux, la toute première partie de logiciel Linux qui estchargée est le noyau. Le noyau initialise les composants matériels dusystème comme les ports série, les ports parallèles, les cartes son,les cartes réseau, les contrôleurs IDE, les contrôleurs SCSI et beaucoupd'autres choses. En bref, le noyau rend le matériel disponible pour quele logiciel puisse fonctionner.</para></sect4><sect4><title>entêtes du noyau linux</title><para>Nous copions ces fichiers dans /usr/include/(linux,asm) lors duchapitre 5. Ils doivent correspondre à ceux avec lesquels glibc a étécompilé et ne doivent <emphasis>pas</emphasis> être remplacé lors d'unemise à jour du kernel. Ils sont essentiels pour compiler un grandnombre de logiciels.</para></sect4></sect3></sect2>