<sect2>
<title>Explication des commandes</title>

<para><command>--enable-build-20</command> :
Construit la version compatible Motif 2.0 des bibliothèques lesstif.</para>

<para><command>--enable-build-21</command> :
Construit aussi les versions comatible Motif 2.1.</para>

<para><command>--disable-debug</command> :
Ne génère pas d'informations de débuggage.</para> 

<para><command>--enable-production</command> :
Construit la release des bibliothèques lesstif.</para> 

<para><command>--disable-build-tests</command> :
Ne construit pas l'arbre test/ (voir note de tests ci-dessous).</para> 

<para><command>--with-xdnd</command> :
Active le support de la compatibilité XDND Gnome.</para> 

</sect2>

