<sect2>
<title>Introduction à oaf</title>

<screen>Site de téléchargement (HTTP):       <ulink url="&oaf-download-http;"/>
Site de téléchargement (FTP):        <ulink url="&oaf-download-ftp;"/>
Version utilisée:                   &oaf-version;
Taille du package:                   &oaf-size;
Estimation de l'espace disque requis:  &oaf-buildsize;</screen>

<para>Le package oaf contient le 'Object Activation Framework' pour GNOME.</para>

<screen>oaf dépend de
<xref linkend="ORBit"/> et <xref linkend="libxml"/>
oaf utilisera
<xref linkend="gtk-doc"/></screen>

</sect2>
