<sect2>
<title>Contenu</title>

<para>Le package pciutils contient <userinput>lspci</userinput> et
<userinput>setpci</userinput>.</para>

</sect2>

<sect2><title>Description</title>

<sect3><title>lspci</title>
<para>lspci est un utilitaire pour afficher des informations sur tous les
bus PCI sur le système et tous les périphériques qui y sont connectés.
</para></sect3>

<sect3><title>setpci</title>
<para>setpci est un utilitaire pour accéder et configurer aux périphériques
PCI.</para></sect3>

</sect2>

