<sect2>
<title>Introduction à alsa-utils</title>

<screen>Site de téléchargement (HTTP):       <ulink url="&alsa-utils-download-http;"/>
Site de téléchargement (FTP):        <ulink url="&alsa-utils-download-ftp;"/>
Version utilisée:                   &alsa-utils-version;
Taille du package:                   &alsa-utils-size;
Estimation de l'espace disque requis:  &alsa-utils-buildsize;</screen>

<para>Le package alsa-utils contient différents utilitaires utiles pour
contrôler votre carte son.</para>

<screen>alsa-utils dépend de
<xref linkend="alsa-lib"/>.</screen>

</sect2>
