<?xml version="1.0" encoding="UTF-8"?>
<!DOCTYPE sect1 PUBLIC "-//OASIS//DTD DocBook XML V4.5//EN"
   "http://www.oasis-open.org/docbook/xml/4.5/docbookx.dtd" [
  <!ENTITY % general-entities SYSTEM "../../general.ent">
  %general-entities;
  <!ENTITY imagemagick-patch-version "1">
  <!-- Not sure what to do here as ImageMagick is one of the fastest-moving
       targets in all of open-source. One solution is to always use the last
       version of a specific major-minor from the 'legacy' subdirectory of
       the path in these URL's. Otherwise these links are broken within days
       after updates :-(  Unfortunately, versions always roll on after patch
       version 10, whether or not significant changes occur, and it takes
       time before versions migrate to legacy/  -->
  <!ENTITY imagemagick-download-http " ">
  <!ENTITY imagemagick-download-ftp  "ftp://ftp.imagemagick.org/pub/ImageMagick/ImageMagick-&imagemagick-version;-&imagemagick-patch-version;.tar.xz">
  <!ENTITY imagemagick-md5sum        "bde038ae05fb20d29cebf88ab9cbdce5">
  <!ENTITY imagemagick-size          "7.2 Mo">
  <!ENTITY imagemagick-buildsize     "147 Mo (with typical dependencies, additional 25 Mo to run the test suite, reputedly 450 Mo with all dependencies)">
  <!ENTITY imagemagick-time          "2.5 SBU (typical build - ajouter 8.1 SBU pour lancer la suite de tests and 15 SBU to run the validation suite)">
]>
<sect1 id="imagemagick"
xreflabel="ImageMagick-&imagemagick-version;-&imagemagick-patch-version;">
  <?dbhtml filename="imagemagick.html"?>
  <sect1info>
    <othername>$LastChangedBy&nbsp;: randy $</othername>
    <date>$Date&nbsp;: 2013-02-10 18:24:28 +0100 (Sun, 10 Feb 2013) $</date>
  </sect1info>
  <title>ImageMagick-&imagemagick-version;-&imagemagick-patch-version;</title>
  <indexterm zone="imagemagick">
    <primary sortas="a-ImageMagick">ImageMagick</primary>
  </indexterm>
  <sect2 role="package">
    <title>Introduction à ImageMagick</title>
    <para><application>ImageMagick</application> est un ensemble d'outils
    et de bibliothèques pour lire, écrire et manipuler une image dans divers formats image. Les
    opérations de traitement d'images sont disponibles en ligne de commande.
    Des liaisons pour Perl et C++ sont également disponibles.</para>
   &lfs75_checked;
    <bridgehead renderas="sect3">Informations sur le paquet</bridgehead>
    <itemizedlist spacing="compact">
      <listitem>
        <para>Téléchargement (HTTP)&nbsp;: <ulink url="&imagemagick-download-http;"/></para>
      </listitem>
      <listitem>
        <para>Téléchargement (FTP)&nbsp;: <ulink url="&imagemagick-download-ftp;"/></para>
      </listitem>
      <listitem>
        <para>Somme de contrôle MD5 du téléchargement&nbsp;: &imagemagick-md5sum;</para>
      </listitem>
      <listitem>
        <para>Taille du téléchargement&nbsp;: &imagemagick-size;</para>
      </listitem>
      <listitem>
        <para>Estimation de l'espace disque requis&nbsp;: &imagemagick-buildsize;</para>
      </listitem>
      <listitem>
        <para>Estimation du temps de construction&nbsp;: &imagemagick-time;</para>
      </listitem>
    </itemizedlist>
    <note><para>Les sources de <application>ImageMagick</application> sont
    mises à jour fréquemment et la version affichée ci-dessus peut ne plus être
    disponible sur les emplacements de téléchargement. Vous pouvez télécharger
    une version plus récente et utiliser les instructions de BLFS pour l'installer.
    Il y a des chances que cela fonctionne très bien, mais n'a pas été testé par l'équipe
    BLFS. Si la version du paquet affichée ci-dessus n'est pas disponible aux emplacements
    indiqués ci-dessus ou dans le répertoire <filename class='directory'>legacy/</filename> sur
    <literal>ftp.ImageMagick.org/pub/ImageMagick</literal>, vous pouvez la télécharger sur le serveur de paquets
    BLFS à <ulink
    url="&sources-anduin-http;/i/ImageMagick-&imagemagick-version;-&imagemagick-patch-version;.tar.xz"/>.
    </para></note>
    <bridgehead renderas="sect3">Dépendances d'ImageMagick</bridgehead>
    <bridgehead renderas="sect4">Recommandées</bridgehead>
    <para role="recommended">
               <xref linkend="x-window-system"/>
</para>
    <para>Vous devriez installer les dépendances facultatives listées ci-dessous 
    si vous avez besoin du support d'un format spécifique ou de l'outil de
    conversion que la dépendance fournit. Beaucoup de possibilités et d'usage
    des dépendances sont décrites dans la section 
    <quote>MAGICK DELEGATES</quote> du fichier
    <filename>README.txt</filename> situé dans l'arborescence du source. Vous
    pouvez trouver des informations supplémentaires sur les dépendances tant dans le fichier
    <filename>Install-unix.txt</filename> situé dans l'arborescence
    des sources qu'en lançant la commande <command>./configure --help</command>.
    Vous pouvez lire un résumé de ces information et des remarques complémentaires
    en ligne sur <ulink
    url="http://www.imagemagick.org/script/advanced-unix-installation.php"/>.</para>
    <bridgehead renderas="sect4">Utilitaires systèmes facultatifs</bridgehead>
    <para role="optional">
      <xref linkend="cups"/>,
      <xref linkend="curl"/>,
      <ulink url="http://dmalloc.com/">Dmalloc</ulink>,
      <ulink url="http://linux.softpedia.com/get/Programming/Debuggers/Electric-Fence-3305.shtml/">Electric Fence</ulink>
      <xref linkend="ffmpeg"/>,
      <ulink url="http://www.fftw.org/">FFTW</ulink>,
      <ulink url="http://www.mupdf.com/">MuPDF</ulink>,
      <ulink url="http://www.openpgp.org/resources/downloads">PGP</ulink> 
      ou <xref linkend="gnupg2"/>
     (vous devrez faire quelques hacks pour utiliser <application>GnuPG</application>),
      <xref linkend="p7zip"/> (LZMA),
       <ulink url="ftp://ftp.imagemagick.org/pub/ImageMagick/delegates/profiles.zip">Profiles</ulink>,
       <xref linkend="sane"/>,
      <ulink url="http://ufraw.sourceforge.net/">ufraw</ulink> (pour les formats raw listés dans
      <filename>www/formats.html</filename>),
      <xref linkend="wget"/>, et
      <xref linkend="xdg-utils"/>
     </para>
    <bridgehead renderas="sect4">Bibliothèques graphiques facultatives</bridgehead>
    <para role="optional">
      <ulink url="http://corefonts.sourceforge.net/">corefonts</ulink>,
      <ulink url="http://djvu.sourceforge.net/">DjVuLibre</ulink>,
      
      <ulink url="ftp://ftp.imagemagick.org/pub/ImageMagick/delegates/">
      FlashPIX (libfpx)</ulink>,
      
      <xref linkend="jasper"/>,
      <ulink url="http://www.cl.cam.ac.uk/~mgk25/jbigkit/">JBIG-KIT</ulink>,
      <xref linkend="lcms"/> or
      <xref linkend="lcms2"/>,
      <xref linkend="libexif"/>,
      <xref linkend="libjpeg"/>,
      <xref linkend="libpng"/>,
      <xref linkend="librsvg"/>,
      <xref linkend="libtiff"/>,
      <xref linkend="libwebp"/>,
      <ulink url="http://liblqr.wikidot.com/en:download-page">Liquid Rescale</ulink>,
      <ulink url="http://www.openexr.com/">OpenEXR</ulink>,
      <xref linkend="openjpeg"/>,
      <xref linkend="pango"/>, et
      <ulink url="http://www.agocg.ac.uk/train/cgm/ralcgm.htm">RALCGM</ulink>
     (ou <ulink url="http://www.mcmurchy.com/ralcgm/ralcgm-3.51.tar.gz">ralcgm</ulink>)
      </para>
    <bridgehead renderas="sect4">Utilitaires graphiques facultatifs</bridgehead>
    <para role="optional">
      <ulink url="http://www.blender.org/">Blender</ulink>,
      <ulink url="http://dejavu.sourceforge.net/">DejaVu fonts</ulink>,
      <ulink url="http://www.ghostscript.com/download/gpcldnld.html">GhostPCL</ulink> or
      <ulink url="http://www.ghostscript.com/download/gpdldnld.html">GhostPDL</ulink>,
      <xref linkend="gs"/>,
      <xref linkend="gimp"/>,
      <ulink url="http://www.gnuplot.info/">Gnuplot</ulink>,
      <xref linkend="graphviz"/>,
      <xref linkend="inkscape"/>,
      <ulink url="http://www.povray.org/">POV-Ray</ulink>, et
      <ulink url="http://radsite.lbl.gov/radiance/HOME.html">Radiance</ulink>
    </para>
    <bridgehead renderas="sect4">Outils de conversion facultatifs</bridgehead>
    <para role="optional">
      <ulink url="http://autotrace.sourceforge.net/">AutoTrace</ulink>,
      <xref linkend="enscript"/>,
     <ulink url="http://www.lizardtech.com/downloads/category/">
      Les utilitaires en ligne de commande de GeoExpress, les utilitaires de AKA MrSID (paquet binaire)</ulink>,
      <ulink url="http://www.gnu.org/software/hp2xx/">hp2xx</ulink>,
     <ulink url="http://user.it.uu.se/~jan/html2ps.html">html2ps</ulink>,
     <ulink url="http://wvware.sourceforge.net/">libwmf</ulink>,
      <ulink url="http://www.mpeg.org/MSSG/">MPEG-2 Video Codec</ulink>,
      <ulink url="http://netpbm.sourceforge.net/">Netpbm</ulink>,
      <xref linkend="texlive"/>,
      <ulink url="http://www.xfig.org/">Transfig</ulink>,
      
      <ulink url="http://sk1project.org/modules.php?name=products&amp;product=uniconvertor">
      UniConvertor</ulink>, et
     <ulink url="http://www.cs.utah.edu/gdc/projects/urt/">Utah Raster Toolkit</ulink>
      (ou <ulink url="http://www.mcmurchy.com/urt/urt-3.1b.tar.gz">URT-3.1b</ulink>)
    </para>
    <para condition="html" role="usernotes">Notes utilisateur&nbsp;:
    <ulink url="&blfs-wiki;/imagemagick"/></para>
  </sect2>
  <sect2 role="installation">
    <title>Installation de ImageMagick</title>
    <para>Installez <application>Imagemagick</application> en lançant les commandes
    suivantes&nbsp;:</para>
 
<screen>
<userinput>./configure --prefix=/usr                 --sysconfdir=/etc             --with-modules                --with-perl                   --disable-static  &amp;&amp;
make</userinput>
</screen>
     <para>Maintenant, en tant qu'utilisateur <systemitem class="username">root</systemitem>&nbsp;:</para>
<screen role="root">
<userinput>make install</userinput>
</screen>
    <para>
      Pour tester l'installation, tapez : <command>make check</command>. Pour des tests plus comprehensibles, 
      lancez la suite de validation de <application>ImageMagick</application>
      , après que le paquet est installé. Notez que les tests EPS,
      PS, et PDF demandent un 
      <application>Ghostscript</application> fonctionnel.  un test demande
      "Helvetica" de
      "Standard Fonts" qui est facultativement insallé par <xref linkend="gs"/>.
    </para>
    
    
  </sect2>
  <sect2 role="commands">
    <title>Explication des commandes</title>
    <para>
      <parameter>--sysconfdir=/etc</parameter>&nbsp;: Installe les fichiers de configuration 
      <filename class="extension">.xml</filename> dans
      <filename class='directory'>/etc/ImageMagick</filename> au lieu de 
      <filename class='directory'>/usr/etc/ImageMagick</filename> par défaut.
    </para>
    <para><parameter>--with-modules</parameter>&nbsp;: Active le support des
    modules chargeables de façon dynamique.</para>
    <para><parameter>--with-perl</parameter>&nbsp;: Active la construction et l'installation
    de PerlMagick.</para>
    <para>
      <parameter>--disable-static</parameter>&nbsp;: Empêche la construction et l'installation des
      bibliothèques statiques.
    </para>
    
    <para>
      <option>--with-gslib=/usr/lib</option>&nbsp;: Active le support pour utiliser la bibliothèque partagée de 
      <application>Ghostscript</application>.
    </para>
    <para>
      <option>--with-rsvg</option>&nbsp;: Active le support pour utiliser la bibliothèque
      <application>librsvg</application>.
    </para>
    <para>
      <option>--with-autotrace</option>&nbsp;: Active le support pour utiliser la bibliothèque
      <application>Autotrace</application>.
    </para>
    <para>
      <option>--with-wmf</option>&nbsp;: Active le support pour utiliser la bibliothèque
      <application>libwmf</application>.
    </para>
    <para>
      <option>--with-gvc</option>&nbsp;: Active le support pour utiliser
      <application>GraphViz</application>.
    </para>
    <para><option>--with-windows-font-dir=<replaceable>&lt;Un/Répertoire&gt;</replaceable></option>&nbsp;:
    Cette option spécifie le répertoire où les CoreFonts Windows 
    seront installés.</para>
    <para>
      <option>--with-dejavu-font-dir=
      <replaceable>&lt;Some/Directory&gt;</replaceable></option>&nbsp;:
      Cette option spécifie le répertoire ou les polices DejaVu sont isntallées.
    </para>
   <para>Les options et les paramètres listés ci-dessus sont les seuls que vous devriez
    être obligé de passer au script <command>configure</command> pour activer toutes les fonctions
    déléguées aux dépendances. Toutes les autres dépendances seront automatiquement
    détectées et utilisées dans la construction si elles sont installées.</para>
  </sect2>
  <sect2 role="content">
    <title>Contenu</title>
    <segmentedlist>
      <segtitle>Programmes installés</segtitle>
      <segtitle>Bibliothèques installées</segtitle>
      <segtitle>Répertoires installés</segtitle>
      <seglistitem>
        <seg>animate, compare, composite, conjure, convert, display,
         identify, import, Magick-config, Magick++-config, MagickCore-config,
        MagickWand-config, mogrify, montage, stream et Wand-config</seg>
        <seg>libMagickCore-6.Q16.so, libMagickWand-6.Q16.so,
        libMagick++-6.Q16.so,
        et de nombreux modules dans
        /usr/lib/ImageMagick-&imagemagick-version;/modules-Q16/{coders,filters}/,
        /usr/lib/perl5/site_perl/&lfs-perl-version;/auto/Image/Magick/Magick.so, et
        /usr/lib/perl5/site_perl/&lfs-perl-version;/auto/Image/Magick/Q16/Q16.so</seg>
        
        <seg>/etc/ImageMagick-6,
        /usr/include/ImageMagick-6,
        /usr/lib/ImageMagick-&imagemagick-version;,
        /usr/lib/perl5/site_perl/&lfs-perl-version;/auto/Image,
        /usr/lib/perl5/site_perl/&lfs-perl-version;/Image/Magick,
        /usr/share/ImageMagick-6 and
        /usr/share/doc/ImageMagick-6</seg>
      </seglistitem>
    </segmentedlist>
    <variablelist>
      <bridgehead renderas="sect3">Descriptions courtes</bridgehead>
      <?dbfo list-presentation="list"?>
      <?dbhtml list-presentation="table"?>
    <varlistentry id="animate">
      <term><command>animate</command></term>
      <listitem>
        <para>anime une séquence d'images.</para>
        <indexterm zone="imagemagick animate">
          <primary sortas="b-animate">animate</primary>
        </indexterm>
      </listitem>
    </varlistentry>
    <varlistentry id="compare">
      <term><command>compare</command></term>
      <listitem>
        <para>compare une image à une image reconstruite.</para>
        <indexterm zone="imagemagick compare">
          <primary sortas="b-compare">compare</primary>
        </indexterm>
      </listitem>
    </varlistentry>
    <varlistentry id="composite">
      <term><command>composite</command></term>
      <listitem>
        <para>assemble diverses images sur l'image de base donnée.</para>
        <indexterm zone="imagemagick composite">
          <primary sortas="b-composite">composite</primary>
        </indexterm>
      </listitem>
    </varlistentry>
    <varlistentry id="conjure">
      <term><command>conjure</command></term>
      <listitem>
        <para>exécute un script MSL pour créer une image.</para>
        <indexterm zone="imagemagick conjure">
          <primary sortas="b-conjure">conjure</primary>
        </indexterm>
      </listitem>
    </varlistentry>
    <varlistentry id="convert">
      <term><command>convert</command></term>
      <listitem>
        <para>convertit une/des image(s) d'un format en un autre.</para>
        <indexterm zone="imagemagick convert">
          <primary sortas="b-convert">convert</primary>
        </indexterm>
      </listitem>
    </varlistentry>
    <varlistentry id="display">
      <term><command>display</command></term>
      <listitem>
        <para>affiche une image.</para>
        <indexterm zone="imagemagick display">
          <primary sortas="b-display">display</primary>
        </indexterm>
      </listitem>
    </varlistentry>
    <varlistentry id="identify">
      <term><command>identify</command></term>
      <listitem>
        <para>décrit le format et les caractéristiques d'un fichier image.</para>
        <indexterm zone="imagemagick identify">
          <primary sortas="b-identify">identify</primary>
        </indexterm>
      </listitem>
    </varlistentry>
    <varlistentry id="import">
      <term><command>import</command></term>
      <listitem>
        <para>captures une fenêtre X.</para>
        <indexterm zone="imagemagick import">
          <primary sortas="b-import">import</primary>
        </indexterm>
      </listitem>
    </varlistentry>
    <varlistentry id="magick-config">
     <term><command>Magick{,++,Core,Wand}-config</command></term>
     <listitem>
        <para>montre des information sur les versions installées des bibliothèques
        <application>ImageMagick</application> Magick++.</para>
        <indexterm zone="imagemagick magick-config">
          <primary sortas="b-Magick-config">Magick-config</primary>
        </indexterm>
      </listitem>
    </varlistentry>
    <varlistentry id="mogrify">
      <term><command>mogrify</command></term>
      <listitem>
        <para>transforme une image.</para>
        <indexterm zone="imagemagick mogrify">
          <primary sortas="b-mogrify">mogrify</primary>
        </indexterm>
      </listitem>
    </varlistentry>
    <varlistentry id="montage">
      <term><command>montage</command></term>
      <listitem>
        <para>rassemble plusieurs images sur une nouvelle image.</para>
        <indexterm zone="imagemagick montage">
          <primary sortas="b-montage">montage</primary>
        </indexterm>
      </listitem>
    </varlistentry>
    <varlistentry id="stream">
      <term><command>stream</command></term>
      <listitem>
        <para>met en flux un ou plusieurs composants de pixels d'une image ou
         une portion de l'image vers des formats de stockage de votre choix.</para>
        <indexterm zone="imagemagick stream">
          <primary sortas="b-stream">stream</primary>
        </indexterm>
      </listitem>
    </varlistentry>
    <varlistentry id="wand-config">
      <term><command>Wand-config</command></term>
      <listitem>
        <para>montre les options requises pour utiliser la bibliothèque Wand.</para>
        <indexterm zone="imagemagick wand-config">
          <primary sortas="b-Wand-config">Wand-config</primary>
        </indexterm>
      </listitem>
    </varlistentry>
    <varlistentry id="perlmagick">
      <term><filename class='libraryfile'>Image::Magick</filename></term>
      <listitem>
        <para>permet de lire, manipuler et écrire un grand nombre de formats de fichiers
        images en utilisant la bibliothèque <application>ImageMagick</application>.
        Lancez <command>make</command> dans le répertoire
        <filename class='directory'>PerlMagick/demo</filename>
        de l'arborescence des sources du paquet après que le paquet a été installé
        pour voir une belle démonstration des fonctionnalités du module.</para>
        <indexterm zone="imagemagick perlmagick">
          <primary sortas="g-Image-Magick">Image::Magick</primary>
        </indexterm>
      </listitem>
    </varlistentry>
    </variablelist>
  </sect2>
</sect1>
