<?xml version="1.0" encoding="UTF-8"?>
<!DOCTYPE sect1 PUBLIC "-//OASIS//DTD DocBook XML V4.5//EN"
   "http://www.oasis-open.org/docbook/xml/4.5/docbookx.dtd" [
  <!ENTITY % general-entities SYSTEM "../../../general.ent">
  %general-entities;

  <!ENTITY my-download-http "&metacpan_authors;/P/PL/PLICEASE/Alien-Libxml2-&Alien-Libxml2-version;.tar.gz">
  <!ENTITY my-md5sum "5fee0bd3a987a1e7f40ce50016c10c8a">

]>

  
  <!-- Begin Alien::Libxml2 -->
<sect2 id="perl-alien-libxml2" xreflabel="Alien-Libxml2-&Alien-Libxml2-version;">

    <title>Alien::Libxml2-&Alien-Libxml2-version;</title>

    <indexterm zone="perl-alien-libxml2">
      <primary sortas="a-Alien-Libxml2">Alien::Libxml2</primary>
    </indexterm>

    <sect3 role="package">
      <title>Introduction à Alien::Libxml2</title>

      <para>
        Alien::Libxml2 est conçu pour permettre à des modules d'installer la
bibliothèque C libxml2 sur votre système. Dans BLFS, il utilise
<command>pkg-config</command> pour trouver comment se lier à la bibliothèque
<xref linkend="libxml2"/> installée.
      </para>

      &lfs111_checked;

      <bridgehead renderas="sect4">Informations sur le paquet</bridgehead>
      <itemizedlist spacing="compact">
        <listitem>
          <para>
            Téléchargement (HTTP)&nbsp;: <ulink url="&my-download-http;"/>
          </para>
        </listitem>
        <listitem>
          <para>
            Somme de contrôle MD5 du téléchargement&nbsp;: &my-md5sum;
          </para>
        </listitem>
      </itemizedlist>

      <bridgehead renderas="sect4">Dépendances de Alien::Libxml2</bridgehead>

      <bridgehead renderas="sect5">Requises</bridgehead>
      <para role="required">
        <xref linkend="perl-alien-build"/>, <xref linkend="libxml2"/>, <xref
linkend="perl-path-tiny"/>
      </para>

      <bridgehead renderas="sect5">Recommandées (requises pour la suite de tests)</bridgehead>
      <para role="recommended">
        <xref linkend="perl-test2-suite"/>
      </para>

    </sect3>

    <sect3 role="installation">
      <title>Installation de Alien::Libxml2</title>

      <xi:include xmlns:xi="http://www.w3.org/2001/XInclude"
                  href="../../../xincludes/perl-standard-install.xml"/>

    </sect3>

  </sect2>
