<?xml version="1.0" encoding="ISO-8859-1"?>
<!DOCTYPE appendix PUBLIC "-//OASIS//DTD DocBook XML V4.3//EN" "http://www.oasis-open.org/docbook/xml/4.3/docbookx.dtd" [
  <!ENTITY % general-entities SYSTEM "../general.ent">
  %general-entities;
]>
<appendix id="appendixb" xreflabel="Appendix B">
<?dbhtml dir="appendixb"?>
<title>Remerciements</title>
<?dbhtml filename="acknowledgements.html"?>

<para>Nous aimerions remercier les personnes et organisations suivantes pour
leur contributions au projet Linux From Scratch.</para>

<itemizedlist>

<listitem><para><ulink url="mailto:gerard@linuxfromscratch.org">Gerard
Beekmans</ulink> &lt;gerard@linuxfromscratch.org&gt; &ndash; créateur de LFS,
leader du projet</para></listitem>

<listitem><para><ulink url="mailto:matthew@linuxfromscratch.org">Matthew
Burgess</ulink> &lt;matthew@linuxfromscratch.org&gt; &ndash; leader du projet
LFS, rédacteur technique LFS, gestionnaire des versions de LFS</para></listitem>

<listitem><para><ulink url="mailto:archaic@linuxfromscratch.org">Archaic</ulink>
&lt;archaic@linuxfromscratch.org&gt; &ndash; rédacteur technique LFS, leader du
projet HLFS, rédacteur BLFS, mainteneur des projets Astuces et Correctifs
</para></listitem>

<listitem><para><ulink url="mailto:nathan@linuxfromscratch.org">Nathan
Coulson</ulink> &lt;nathan@linuxfromscratch.org&gt; &ndash; Mainteneur de
LFS-Bootscripts</para></listitem>

<listitem><para><ulink url="mailto:bdubbs@linuxfromscratch.org">Bruce
Dubbs</ulink> &lt;bdubbs@linuxfromscratch.org&gt; &ndash; leader du projet BLFS
</para></listitem>

<listitem><para><ulink url="mailto:manuel@linuxfromscratch.org">Manuel
Canales Esparcia</ulink> &lt;manuel@linuxfromscratch.org&gt; &ndash;
mainteneur des fichiers XML et XSL pour LFS/BLFS/HLFS</para></listitem>

<listitem><para><ulink url="mailto:jim@linuxfromscratch.org">Jim
Gifford</ulink> &lt;jim@linuxfromscratch.org&gt; &ndash; rédacteur technique
LFS, leader du projet Correctifs</para></listitem>

<listitem><para><ulink url="mailto:jhuntwork@linuxfromscratch.org">Jeremy
Huntwork</ulink> &lt;jhuntwork@linuxfromscratch.org&gt; &ndash; rédacteur
technique LFS, mainteneur du LiveCD LFS, leader du projet ALFS</para></listitem>

<listitem><para><ulink url="mailto:lizardo@linuxfromscratch.org">Anderson
Lizardo</ulink> &lt;lizardo@linuxfromscratch.org&gt; &ndash; mainteneur des
scripts du site web</para></listitem>

<listitem><para><ulink url="mailto:ryan@linuxfromscratch.org">Ryan
Oliver</ulink> &lt;ryan@linuxfromscratch.org&gt; &ndash; mainteneur des outils
de production LFS</para></listitem>

<listitem><para><ulink url="mailto:jwrober@linuxfromscratch.org">James
Robertson</ulink> &lt;jwrober@linuxfromscratch.org&gt; &ndash; mainteneur de
Bugzilla</para></listitem>

<listitem><para><ulink url="mailto:tushar@linuxfromscratch.org">Tushar
Teredesai</ulink> &lt;tushar@linuxfromscratch.org&gt; &ndash; rédacteur en chef
de BLFS, leader des projets Astuces et Correctifs</para></listitem>

</itemizedlist>

<bridgehead renderas="sect2">Traducteurs</bridgehead>

<itemizedlist>

<listitem><para><ulink url="mailto:macana@lfs-es.org">Manuel Canales
Esparcia</ulink> &lt;macana@lfs-es.org&gt; &ndash; projet de traduction
espagnol</para></listitem>

<listitem><para><ulink url="mailto:johan@linuxfromscratch.org">Johan
Lenglet</ulink> &lt;johan@linuxfromscratch.org&gt; &ndash; projet de traduction
français</para></listitem>

<listitem><para><ulink
url="mailto:lizardo@linuxfromscratch.org">Anderson Lizardo</ulink>
&lt;lizardo@linuxfromscratch.org&gt; &ndash; projet de traduction
portugais</para></listitem>

<listitem><para><ulink url="mailto:tr@erdfunkstelle.de">Thomas
Reitelbach </ulink> &lt;tr@erdfunkstelle.de&gt; &ndash; projet de traduction
allemand</para> </listitem>

</itemizedlist>

<bridgehead renderas="sect2">Mainteneurs des miroirs</bridgehead>

<bridgehead renderas="sect3">Miroirs d'Amérique du Nord</bridgehead>

<itemizedlist>

<listitem><para><ulink url="mailto:scott@osuosl.org">Scott
Kveton</ulink> &lt;scott@osuosl.org&gt; &ndash; miroir lfs.oregonstate.edu
</para></listitem>

<listitem><para><ulink url="mailto:miha@xuy.biz">Mikhail
Pastukhov</ulink> &lt;miha@xuy.biz&gt; &ndash; miroir lfs.130th.net
</para></listitem>

<listitem><para><ulink url="mailto:lost@l-w.net">William Astle</ulink>
&lt;lost@l-w.net&gt; &ndash; miroir ca.linuxfromscratch.org
</para></listitem>

<listitem><para><ulink url="mailto:jpolen@rackspace.com">Jeremy
Polen</ulink> &lt;jpolen@rackspace.com&gt; &ndash; miroir
us2.linuxfromscratch.org</para></listitem>

<listitem><para><ulink url="mailto:tim@idge.net">Tim Jackson</ulink>
&lt;tim@idge.net&gt; &ndash; miroir linuxfromscratch.idge.net
</para></listitem>

<listitem><para><ulink url="mailto:jeremy@linux-phreak.net">Jeremy
Utley </ulink> &lt;jeremy@linux-phreak.net&gt; &ndash; miroir
lfs.linux-phreak.net</para></listitem>

</itemizedlist>

<bridgehead renderas="sect3">Miroirs d'Amérique du Sud</bridgehead>

<itemizedlist>

<listitem><para><ulink url="mailto:manuel@linuxfromscratch.org">Manuel
Canales Esparcia</ulink> &lt;manuel@linuxfromscratch.org&gt; &ndash;
miroir lfsmirror.lfs-es.org</para></listitem>

<listitem><para><ulink url="mailto:sysop@mesi.com.ar">Andres
Meggiotto</ulink> &lt;sysop@mesi.com.ar&gt; &ndash; miroir lfs.mesi.com.ar
</para></listitem>

<listitem><para><ulink url="mailto:ebf@aedsolucoes.com.br">Eduardo B.
Fonseca</ulink> &lt;ebf@aedsolucoes.com.br&gt; &ndash;
miroir br.linuxfromscratch.org</para></listitem>

</itemizedlist>

<bridgehead renderas="sect3">Miroirs européens</bridgehead>

<itemizedlist>

<listitem><para><ulink url="mailto:barna@siker.hu">Barna
Koczka</ulink> &lt;barna@siker.hu&gt; &ndash; miroir hu.linuxfromscratch.org
</para></listitem>

<listitem><para><ulink url="http://www.mirror.ac.uk">UK Mirror
Service</ulink> &ndash; miroir linuxfromscratch.mirror.ac.uk
</para></listitem>

<listitem><para><ulink url="mailto:Martin.Voss@ada.de">Martin
Voss</ulink> &lt;Martin.Voss@ada.de&gt; &ndash; miroir lfs.linux-matrix.net
</para></listitem>

<listitem><para><ulink url="mailto:guido@primerelay.net">Guido
Passet</ulink> &lt;guido@primerelay.net&gt; &ndash; miroir
nl.linuxfromscratch.org</para></listitem>

<listitem><para><ulink url="mailto:baafie@planet.nl">Bastiaan
Jacques</ulink> &lt;baafie@planet.nl&gt; &ndash; miroir lfs.pagefault.net
</para></listitem>

<listitem><para><ulink
url="mailto:lfs-mirror@linuxfromscratch.rave.org">Roel Neefs</ulink>
&lt;lfs-mirror@linuxfromscratch.rave.org&gt; &ndash;
miroir linuxfromscratch.rave.org</para></listitem>

<listitem><para><ulink url="mailto:justin@jrknierim.de">Justin
Knierim</ulink> &lt;justin@jrknierim.de&gt; &ndash; miroir www.lfs-matrix.de
</para></listitem>

<listitem><para><ulink url="mailto:stevie@stevie20.de">Stephan
Brendel</ulink> &lt;stevie@stevie20.de&gt; &ndash; miroir
lfs.netservice-neuss.de</para></listitem>

<listitem><para><ulink
url="mailto:Antonin.Sprinzl@tuwien.ac.at">Antonin Sprinzl</ulink>
&lt;Antonin.Sprinzl@tuwien.ac.at&gt; &ndash; miroir at.linuxfromscratch.org
</para></listitem>

<listitem><para><ulink url="mailto:fredan-lfs@fredan.org">Fredrik
Danerklint</ulink> &lt;fredan-lfs@fredan.org&gt; &ndash;
miroir se.linuxfromscratch.org</para></listitem>

<listitem><para><ulink
url="mailto:archive@doc.cs.univ-paris8.fr">Parisian sysadmins</ulink>
&lt;archive@doc.cs.univ-paris8.fr&gt; &ndash; miroir
www2.fr.linuxfromscratch.org</para></listitem>

<listitem><para><ulink url="mailto:velin@zadnik.org">Alexander
Velin</ulink> &lt;velin@zadnik.org&gt; &ndash; miroir bg.linuxfromscratch.org
</para></listitem>

<listitem><para><ulink url="mailto:dirk@securewebservices.co.uk"> Dirk
Webster</ulink> &lt;dirk@securewebservices.co.uk&gt; &ndash;
miroir lfs.securewebservices.co.uk</para></listitem>

<listitem><para><ulink url="mailto:thomas@sofagang.dk">Thomas
Skyt</ulink> &lt;thomas@sofagang.dk&gt; &ndash; miroir dk.linuxfromscratch.org
</para></listitem>

<listitem><para><ulink url="mailto:sime@dot-sime.com">Simon
Nicoll</ulink> &lt;sime@dot-sime.com&gt; &ndash; miroir uk.linuxfromscratch.org
</para>
<beginpage/></listitem>

</itemizedlist>

<bridgehead renderas="sect3">Miroirs Asiatiques</bridgehead>

<itemizedlist>

<listitem><para><ulink url="mailto:pyng@spam.averse.net">Pui
Yong</ulink> &lt;pyng@spam.averse.net&gt; &ndash; miroir sg.linuxfromscratch.org
</para></listitem>

<listitem><para><ulink url="mailto:stuart@althalus.me.uk">Stuart
Harris</ulink> &lt;stuart@althalus.me.uk&gt; &ndash;
miroir lfs.mirror.intermedia.com.sg</para></listitem>

</itemizedlist>

<bridgehead renderas="sect3">Miroirs australiens</bridgehead>

<itemizedlist>

<listitem><para><ulink url="mailto:jason@dstc.edu.au">Jason
Andrade</ulink> &lt;jason@dstc.edu.au&gt; &ndash; miroir au.linuxfromscratch.org
</para></listitem>

</itemizedlist>

<bridgehead renderas="sect2">Anciens membres de l'équipe du projet</bridgehead>

<itemizedlist>

<listitem><para><ulink url="mailto:theladyskye@linuxfromscratch.org">Christine
Barczak</ulink> &lt;theladyskye@linuxfromscratch.org&gt; &ndash; rédactrice
LFS</para></listitem>

<listitem><para>Timothy Bauscher</para></listitem>

<listitem><para>Robert Briggs</para></listitem>

<listitem><para>Ian Chilton</para></listitem>

<listitem><para><ulink url="mailto:jeroen@linuxfromscratch.org">Jeroen
Coumans</ulink> &lt;jeroen@linuxfromscratch.org&gt; &ndash; développeur du site
web, mainteneur de la FAQ</para></listitem>

<listitem><para>Alex Groenewoud &ndash; rédacteur technique LFS</para></listitem>

<listitem><para>Marc Heerdink</para></listitem>

<listitem><para>Mark Hymers</para></listitem>

<listitem><para>Seth W. Klein &ndash; mainteneur de la FAQ</para></listitem>

<listitem><para><ulink url="mailto:nicholas@linuxfromscratch.org">Nicholas
Leippe</ulink> &lt;nicholas@linuxfromscratch.org&gt; &ndash; mainteneur du Wiki
</para></listitem>

<listitem><para>Simon Perreault</para></listitem>

<listitem><para><ulink url="mailto:scot@linuxfromscratch.org">Scot Mc
Pherson</ulink> &lt;scot@linuxfromscratch.org&gt; &ndash; mainteneur de la
passerelle NNTP LFS</para></listitem>

<listitem><para><ulink url="mailto:semzx@newmail.ru">Alexander Patrakov</ulink>
&lt;semzx@newmail.ru&gt; &ndash; rédacteur technique LFS</para></listitem>

<listitem><para><ulink url="mailto:gschafer@zip.com.au">Greg Schafer</ulink> &lt;gschafer@zip.com.au&gt; &ndash; rédacteur technique LFS</para></listitem>

<listitem><para>Jesse Tie-Ten-Quee &ndash; rédacteur technique LFS</para></listitem>

<listitem><para><ulink url="mailto:jeremy@linuxfromscratch.org">Jeremy
Utley</ulink> &lt;jeremy@linuxfromscratch.org&gt; &ndash; rédacteur technique
LFS, mainteneur de Bugzilla, mainteneur des LFS-Bootscripts</para></listitem>

<listitem><para><ulink url="mailto:zwinkles@gmail.com">Zack Winkles</ulink>
&lt;zwinkles@gmail.com&gt; &ndash; rédacteur technique LFS</para></listitem>

</itemizedlist>

<bridgehead renderas="sect2">Un remerciement tout particulier à nos
donateurs</bridgehead>

<itemizedlist>

<listitem><para><ulink url="mailto:dean@vipersoft.co.uk">Dean
Benson</ulink> &lt;dean@vipersoft.co.uk&gt; pour plusieurs
contributions financières</para></listitem>

<listitem><para><ulink url="mailto:hrx@hrxnet.de">Hagen
Herrschaft</ulink> &lt;hrx@hrxnet.de&gt; pour le don d'un système P4 2.2 GHz,
fonctionnant actuellement sous le nom de Lorien</para></listitem>

<listitem><para><ulink url="http://www.vasoftware.com">VA
Software</ulink> qui, sous le titre de <ulink
url="http://www.linux.com">Linux.com</ulink>, a donné une station de travail VA
Linux 420 (ancien StartX SP2)</para></listitem>

<listitem><para>Mark Stone pour le don de Belgarath, le serveur
linuxfromscratch.org</para></listitem>

</itemizedlist>

</appendix>

