<sect2>
<title>Installation de Linux_PAM</title>

<para>Installez Linux_PAM en lançant les commandes suivantes:</para>

<para><screen><userinput>./configure --enable-static-libpam --with-mailspool=/var/mail \
--enable-read-both-confs --sysconfdir=/etc &amp;&amp;
make &amp;&amp;
make install &amp;&amp;
mv /lib/libpam.a /lib/libpam_misc.a /lib/libpamc.a /usr/lib &amp;&amp;
ln -sf ../../lib/libpam.so.&Linux_PAM-version; /usr/lib/libpam.so &amp;&amp;
ln -sf ../../lib/libpam_misc.so.&Linux_PAM-version; /usr/lib/libpam_misc.so &amp;&amp;
ln -sf ../../lib/libpamc.so.&Linux_PAM-version; /usr/lib/libpamc.so</userinput></screen></para>


</sect2>
