<sect2>
<title>Explication des commandes</title>

<para><option>--noninteractive</option> : Cette option
est utilisée pour empêcher le script de demander confirmation
pour les répertoires d'installation (que nous indiquons à
configure avec d'autres options).</para> 

<para><parameter>--with-DIR_MAN=/usr/share/man</parameter> : Ceci est
utilisé parce que, malgré le fait que nous donnons
<parameter>--prefix=/usr</parameter>, la routine configure essaie d'installer
les pages man dans <filename class="directory">/usr/local/man</filename> au lieu
du bon emplacement.</para>

</sect2>

