<sect2>
<title>Introduction à zsh</title>

<screen>Site de téléchargement (HTTP):  <ulink url="&zsh-download-http;"/>
Site de téléchargement (FTP):           <ulink url="&zsh-download-ftp;"/>
Version utilisée:                       &zsh-version;
Taille du package:                      &zsh-size;
Estimation de l'espace disque requis:   &zsh-buildsize;
Estimation du temps de construction:    &zsh-time;</screen>

<para>Le package zsh contient le shell zsh. zsh est un interpréteur de commandes
(shell) utilisable en tant que shell interactif et en tant que processeur de
commandes shell (scripts). Des shells standards, zsh ressemble plus à ksh mais
inclut beaucoup d'améliorations.</para>

</sect2>
