<sect2><title>&nbsp;</title><para>&nbsp;</para></sect2>

<sect2>
<title>Installation de Procps</title>

<para>Ce package nécessite que son correctif lui soit appliqué avant qu'il ne
soit installé. Il corrige un problème de locale qui fait que
<userinput>w</userinput> ne fonctionne pas sous certaines configurations de
locale. Appliquez le correctif:</para>

<para><screen><userinput>patch -Np1 -i ../procps-&procps-patch-version;.patch</userinput></screen></para>

<para>Compilez Procps:</para>

<para><screen><userinput>make</userinput></screen></para>

<para>Finissez l'installation du package:</para>

<para><screen><userinput>make XSCPT="" install</userinput></screen></para>

<para>L'option <emphasis>XSCPT</emphasis> donnera une valeur vide à la variable
XSCPT du Makefile, de façon à ce que l'installation de XConsole est désactivée.
Autrement, <userinput>make install</userinput> essaiera de copier le fichier
XConsole vers /usr/X11R6/lib/X11/app-defaults. Ce répertoire n'existe pas parce
que X n'est pas installé.</para>

</sect2>
