<?xml version="1.0" encoding="UTF-8"?>
<!DOCTYPE sect1 PUBLIC "-//OASIS//DTD DocBook XML V4.5//EN"
  "http://www.oasis-open.org/docbook/xml/4.5/docbookx.dtd" [
  <!ENTITY % general-entities SYSTEM "../../general.ent">
  %general-entities;
]>

<sect1 id="ch-system-less" role="wrap">
  <?dbhtml filename="less.html"?>

  <title>Less-&less-version;</title>

  <indexterm zone="ch-system-less">
    <primary sortas="a-Less">Less</primary>
  </indexterm>

  <sect2 role="package">
    <title/>

    <para>Le paquet Less contient un visualisateur de fichiers
    texte.</para>


  </sect2>

  <sect2 role="installation">
    <title>Installation de Less</title>

    <para os="a">Préparez la compilation de Less&nbsp;:</para>

<screen os="b"><userinput>./configure --prefix=/usr --sysconfdir=/etc</userinput></screen>

    <para os="c">Compilez le paquet&nbsp;:</para>

<screen os="d"><userinput>make</userinput></screen>

    <para os="e">Ce paquet ne fournit pas de suite de tests.</para>

    <para os="f">Installez le paquet&nbsp;:</para>

<screen os="g"><userinput>make install</userinput></screen>

    <para os="h">Déplacez <command>less</command> vers 
    <filename class="directory">/bin</filename>&nbsp;:</para>

<screen os="i"><userinput>mv -v /usr/bin/less /bin</userinput></screen>

  </sect2>

  <sect2 id="contents-less" role="content">
    <title>Contenu de Less</title>

    <segmentedlist>
      <segtitle>Programmes installés</segtitle>

      <seglistitem>
        <seg>less, lessecho, lesskey</seg>
      </seglistitem>
    </segmentedlist>

    <variablelist>
      <bridgehead renderas="sect3">Descriptions courtes</bridgehead>
      <?dbfo list-presentation="list"?>
      <?dbhtml list-presentation="table"?>

      <varlistentry id="less">
        <term><command>less</command></term>
        <listitem>
          <para>Un visualisateur de fichiers. Il affiche le contenu du fichier donné,
          vous permettant d'aller vers le haut et vers le bas, de chercher des chaînes
          et de sauter vers des repères</para>
          <indexterm zone="ch-system-less less">
            <primary sortas="b-less">less</primary>
          </indexterm>
        </listitem>
      </varlistentry>

      <varlistentry id="lessecho">
        <term><command>lessecho</command></term>
        <listitem>
          <para>Nécessaire pour étendre les méta-caractères, comme 
          <emphasis>*</emphasis> et <emphasis>?</emphasis>, dans les noms de 
          fichiers de systèmes Unix</para>
          <indexterm zone="ch-system-less lessecho">
            <primary sortas="b-lessecho">lessecho</primary>
          </indexterm>
        </listitem>
      </varlistentry>

      <varlistentry id="lesskey">
        <term><command>lesskey</command></term>
        <listitem>
          <para>Utilisé pour spécifier les
          associations de touches pour <command>less</command></para>
          <indexterm zone="ch-system-less lesskey">
            <primary sortas="b-lesskey">lesskey</primary>
          </indexterm>
        </listitem>
      </varlistentry>

    </variablelist>

  </sect2>

</sect1>

