<sect2>
<title>Introduction to imlib</title>

<screen>Download location (HTTP):       <ulink url="&imlib-download-http;"/>
Download location (FTP):        <ulink url= "&imlib-download-ftp;"/>
Version used:                   &imlib-version;
Package size:                   &imlib-size;
Estimated Disk space required:  &imlib-buildsize;</screen>

<para>The imlib package contains image libraries. These are useful for
loading, rendering and dithering a wide variety of image data formats.</para>

<screen>imlib depends on: 
<xref linkend="xfree86"/>, <xref linkend="libjpeg"/>, <xref linkend="libtiff"/>, <xref linkend="libungif"/> and <xref linkend="libpng"/>
imlib will utilize: 
<xref linkend="GLib"/>, <xref linkend="GTK"/> and gtk-config if installed prior to imlib.</screen>

</sect2>
