<sect2>
<title>Introduction à gtk-doc</title>

<screen>Site de téléchargement (HTTP):       <ulink url="&gtk-doc-download-http;"/>
Site de téléchargement (FTP):        <ulink url="&gtk-doc-download-ftp;"/>
Version utilisée:                   &gtk-doc-version;
Taille du package:                   &gtk-doc-size;
Estimation de l'espace disque requis:  &gtk-doc-buildsize;</screen>

<para>Le package gtk-doc contient un utilitaire de documentation de code. Ceci
est utile pour l'extraction de commentaires spécialement formatés à partir du
code pour créer une documentation de l'API. Ce package est
<emphasis>optionnel</emphasis>; si il n'est pas installé, les packages ne
construirons pas leur documentation. Si vous choisissez d'installer ce package,
vous devrez suivre l'astuce LFS <ulink
url="http://hints.linuxfromscratch.org/hints/docbook.txt">Installer les DTS et
outils Docbook</ulink> pour centraliser les catalogues, ajouter des modèles
additionnels de dtd et dsssl et installer openjade.</para>

<para>Vous avez aussi besoin d'ajouter la dtd v3.0 à votre collection, et
finalement, vous devez modifier dtd-3.1 en ajoutant <ulink
url="http:www.labs.redhat.com/png/png-support.html">png-support-3.1.dtd</ulink>
à <filename>/usr/share/sgml/docbook/sgml-dtd-3.1</filename> et placé:
<screen>PUBLIC "-//GNOME//DTD DocBook PNG Variant V1.1//EN" "png-support-3.1.dtd"</screen>
dans la section fichier du driver DocBook
<filename>/usr/share/sgml/docbook/sgml-dtd-3.1/catalog</filename>.</para>

<screen>gtk-doc dépends de <xref linkend="openjade"/></screen>

</sect2>
