<?xml version="1.0" encoding="UTF-8"?>
<!DOCTYPE sect1 PUBLIC "-//OASIS//DTD DocBook XML V4.5//EN"
  "http://www.oasis-open.org/docbook/xml/4.5/docbookx.dtd" [
  <!ENTITY % general-entities SYSTEM "../../general.ent">
  %general-entities;
]>

<sect1 id="ch-cross-tools-isl" role="wrap">
  <?dbhtml filename="isl.html"?>

  <title>ISL-&isl-version;</title>

  <indexterm zone="ch-cross-tools-isl">
    <primary sortas="a-ISL">ISL</primary>
    <secondary>cross tools</secondary>
  </indexterm>

  <xi:include xmlns:xi="http://www.w3.org/2001/XInclude"
  href="../../final-system/common/isl.xml"
  xpointer="xpointer(//*[@role='package'])"/>

  <sect2 role="installation">
    <title>Installation d'ISL</title>

    <para>Nous allons installer ISL et CLooG pour activer des fonctionnalités
    supplémentaires pour GCC. Ils ne sont pas absolument nécessaires mais GCC
    peut s'y lier pour activer sa nouvelle fonction de génération de boucle qui
    s'appelle Graphite.</para>

    <para os="a">Préparez la compilation d'ISL&nbsp;:</para>

<screen os="b"><userinput>LDFLAGS="-Wl,-rpath,/cross-tools/lib" \
./configure --prefix=/cross-tools --disable-static \
    --with-gmp-prefix=/cross-tools</userinput></screen>

    <para os="c">Compilez le paquet&nbsp;:</para>

<screen os="d"><userinput>make</userinput></screen>

    <para os="e">Installez le paquet&nbsp;:</para>

<screen os="f"><userinput>make install</userinput></screen>

  </sect2>

  <sect2 role="content">
    <title/>

    <para>Les détails de ce paquet sont situés dans <xref
    linkend="contents-isl" role="."/></para>

  </sect2>

</sect1>
