<?xml version="1.0" encoding="ISO-8859-1"?>
<!DOCTYPE sect1 PUBLIC "-//OASIS//DTD DocBook XML V4.5//EN"
  "http://www.oasis-open.org/docbook/xml/4.5/docbookx.dtd" [
  <!ENTITY % general-entities SYSTEM "../../general.ent">
  %general-entities;
]>

<sect1 id="ch-cross-tools-pkg-config-lite" role="wrap">
  <?dbhtml filename="pkg-config-lite.html"?>

  <title>Pkg-config-lite-&pkg-config-lite-version;</title>

  <indexterm zone="ch-cross-tools-pkg-config-lite">
    <primary sortas="a-Pkg-config-lite">Pkg-config-lite</primary>
    <secondary>outils croisés</secondary>
  </indexterm>

  <xi:include xmlns:xi="http://www.w3.org/2001/XInclude"
  href="../../final-system/common/pkg-config-lite.xml"
  xpointer="xpointer(//*[@role='package'])"/>

  <sect2 role="installation">
    <title>Installation de Pkg-config-lite</title>

    <para os="a">Plusieurs paquets dans le système temporaire utiliseront
    <command>pkg-config</command> pour trouver différentes dépendances requises
    et facultatives. Malheureusement, cela peut engendrer que ses paquets trouvent
    les bibliothèques du système hôte et essayent de se lier à elles, ce qui ne 
    fonctionnera pas. Pour éviter ce problème, nous installerons un binaire
    <command>pkg-config</command> dans <filename class="directory">/cross-tools</filename>
    et le configurerons pour qu'il regarde seulement les fichiers 
    Pkg-config dans
    <filename class="directory">/tools</filename>.</para>

    <para os="b">Preparez Pkg-config-lite pour la compilation:</para>

<screen os="c"><userinput>./configure --prefix=/cross-tools --host=${CLFS_TARGET}\
    --with-pc-path=/tools/lib/pkgconfig:/tools/share/pkgconfig</userinput></screen>

    <variablelist os="d">
      <title>Signification des nouvelles options de configure:</title>

      <varlistentry>
        <term><parameter>--host=${CLFS_TARGET}</parameter></term>
        <listitem>
          <para>Plusieurs paquets que nous compilerons de manière croisée plus tard essayeront
          de chercher <command>${CLFS_TARGET}-pkg-config</command>. Initialiser cette option
          assure que Pkg-config-lite créera un lien dur dans 
          <filename class="directory">/cross-tools/bin</filename> avec ce nom, et qu'il sera utiliser
          à la place des tous les programmes avec des noms similaires qui peuvent exister sur
          l'hôte.
          </para>
        </listitem>
      </varlistentry>

      <varlistentry>
        <term><parameter>--with-pc-path</parameter></term>
        <listitem>
          <para>Cela initialise par défaut PKG_CONFIG_PATH dans
          <filename class="directory">/tools/lib/pkgconfig</filename> et
          <filename class="directory">/tools/share/pkgconfig</filename>.</para>
        </listitem>
      </varlistentry>

    </variablelist>

    <para os="e">Compilez le paquet:</para>

<screen os="f"><userinput>make</userinput></screen>

    <para os="g">Installez le paquet:</para>

<screen os="h"><userinput>make install</userinput></screen>

  </sect2>

  <sect2 role="content">
    <title/>

    <para>Les détails de ce paquet sont dans <xref
    linkend="contents-pkg-config-lite" role="."/></para>

  </sect2>

</sect1>
